setup.py
./mixpanel_gevent_proxy/__init__.py
mixpanel_gevent_proxy.egg-info/PKG-INFO
mixpanel_gevent_proxy.egg-info/SOURCES.txt
mixpanel_gevent_proxy.egg-info/dependency_links.txt
mixpanel_gevent_proxy.egg-info/entry_points.txt
mixpanel_gevent_proxy.egg-info/requires.txt
mixpanel_gevent_proxy.egg-info/top_level.txt
mixpanel_gevent_proxy.egg-info/zip-safe