Metadata-Version: 1.1
Name: mixpanel-gevent-proxy
Version: 1.0
Summary: Mixpanel Gevent Proxy
Home-page: https://github.com/khamin/mixpanel_gevent_proxy
Author: Vitaliy Khamin
Author-email: vitaliykhamin@gmail.com
License: UNKNOWN
Platform: UNKNOWN
Classifier: Operating System :: OS Independent
Classifier: Programming Language :: Python
